MANIFEST.in
README.txt
setup.py
docs/HISTORY.txt
docs/LICENSE.txt
src/silva/__init__.py
src/silva.demo.contentlayout.egg-info/PKG-INFO
src/silva.demo.contentlayout.egg-info/SOURCES.txt
src/silva.demo.contentlayout.egg-info/dependency_links.txt
src/silva.demo.contentlayout.egg-info/namespace_packages.txt
src/silva.demo.contentlayout.egg-info/not-zip-safe
src/silva.demo.contentlayout.egg-info/requires.txt
src/silva.demo.contentlayout.egg-info/top_level.txt
src/silva/demo/__init__.py
src/silva/demo/contentlayout/__init__.py
src/silva/demo/contentlayout/advanced.py
src/silva/demo/contentlayout/configure.zcml
src/silva/demo/contentlayout/one_column.png
src/silva/demo/contentlayout/one_column_models.png
src/silva/demo/contentlayout/templates.py
src/silva/demo/contentlayout/two_columns.png
src/silva/demo/contentlayout/static/advanced.css
src/silva/demo/contentlayout/static/two_columns.css
src/silva/demo/contentlayout/templates/advanceddesign.upt
src/silva/demo/contentlayout/templates/advancedlayout.cpt
src/silva/demo/contentlayout/templates/onecolumn.upt
src/silva/demo/contentlayout/templates/twocolumns.upt