Metadata-Version: 1.1
Name: silva.demo.contentlayout
Version: 3.0c1
Summary: Silva Content Layout demonstration templates
Home-page: https://github.com/silvacms/silva.demo.contentlayout
Author: Infrae
Author-email: info@infrae.com
License: BSD
Platform: UNKNOWN
Classifier: Framework :: Zope2
Classifier: Programming Language :: Python
Classifier: Topic :: Software Development :: Libraries :: Python Modules
